CHANGES.txt
DEPENDENCES.txt
README.txt
setup.py
src/ng/__init__.py
src/ng.registry.egg-info/PKG-INFO
src/ng.registry.egg-info/SOURCES.txt
src/ng.registry.egg-info/dependency_links.txt
src/ng.registry.egg-info/namespace_packages.txt
src/ng.registry.egg-info/not-zip-safe
src/ng.registry.egg-info/requires.txt
src/ng.registry.egg-info/top_level.txt
src/ng/registry/__init__.py
src/ng/registry/configure.zcml
src/ng/registry/interfaces.py
src/ng/registry/ng.registry.txt
src/ng/registry/browser/__init__.py
src/ng/registry/browser/configure.zcml
src/ng/registry/etc/ng.registry-configure.zcml
