Metadata-Version: 1.0
Name: ng.registry
Version: 0.0.1
Summary: Product developed to save any custom parameters
Home-page: http://www.dreambot.ru/product/DreamBotZope3Releases/ng.registry
Author: Andrey Orlov
Author-email: dbdt@dreambot.ru
License: GPL v2.1
Platform: UNKNOWN
Classifier: Environment :: Web Environment
Classifier: Intended Audience :: Developers
Classifier: License :: OSI Approved :: GNU General Public License (GPL)
Classifier: Programming Language :: Python
Classifier: Operating System :: OS Independent
Classifier: Topic :: Internet :: WWW/HTTP
Classifier: Framework :: Zope3
